ckydb/__connection.py
ckydb/__controller.py
ckydb/__exc.py
ckydb/__init__.py
ckydb/__store.py
ckydb-0.0.4.dist-info/LICENSE
ckydb-0.0.4.dist-info/METADATA
ckydb-0.0.4.dist-info/WHEEL
ckydb-0.0.4.dist-info/top_level.txt
ckydb-0.0.4.dist-info/RECORD
