Metadata-Version: 2.1
Name: ckydb
Version: 0.0.4
Summary: A simple fast memory-first thread-safe (or goroutine-safe for Go) key-value embedded database that persist data on disk.
Home-page: https://github.com/sopherapps/ckydb/tree/master/implementations/py_ckydb
Author: Martin Ahindura
Author-email: team.sopherapps@gmail.com
License: MIT
Classifier: License :: OSI Approved :: MIT License
Classifier: Programming Language :: Python :: 3
Classifier: Programming Language :: Python :: 3.7
License-File: LICENSE
